tetris/__init__.py
tetris/cli.py
tetris/tetris.py
tetris_terminal-0.0.1.dist-info/licenses/LICENSE
tetris_terminal-0.0.1.dist-info/METADATA
tetris_terminal-0.0.1.dist-info/WHEEL
tetris_terminal-0.0.1.dist-info/entry_points.txt
tetris_terminal-0.0.1.dist-info/top_level.txt
tetris_terminal-0.0.1.dist-info/RECORD
